SyloraQ/__init__.py
SyloraQ/module.py
SyloraQ/ChromeController/BrowSentinel.py
SyloraQ/ChromeController/__init__.py
SyloraQ/security/__init__.py
SyloraQ/security/security.py
SyloraQ/web/__init__.py
SyloraQ/web/web.py
syloraq-3.4.dist-info/LICENSE
syloraq-3.4.dist-info/METADATA
syloraq-3.4.dist-info/WHEEL
syloraq-3.4.dist-info/top_level.txt
syloraq-3.4.dist-info/RECORD
