Metadata-Version: 2.2
Name: SyloraQ
Version: 3.4
Summary: SyloraQ Python Module One Step Ahead
Home-page: https://syloraq.github.io/SyloraQ
Author: SyloraQ
Author-email: syloraq.official@gmail.com
License: SyloraQ Software Agreement
Keywords: SyloraQ,syloraq,QOL,Quality of life,Easier Python,easy python
Classifier: Programming Language :: Python :: 3
Classifier: Intended Audience :: Developers
License-File: LICENSE
Dynamic: author
Dynamic: author-email
Dynamic: classifier
Dynamic: description
Dynamic: description-content-type
Dynamic: home-page
Dynamic: keywords
Dynamic: license
Dynamic: summary
